azure/mgmt/standbypool/__init__.py
azure/mgmt/standbypool/_client.py
azure/mgmt/standbypool/_configuration.py
azure/mgmt/standbypool/_model_base.py
azure/mgmt/standbypool/_patch.py
azure/mgmt/standbypool/_serialization.py
azure/mgmt/standbypool/_validation.py
azure/mgmt/standbypool/_version.py
azure/mgmt/standbypool/py.typed
azure/mgmt/standbypool/aio/__init__.py
azure/mgmt/standbypool/aio/_client.py
azure/mgmt/standbypool/aio/_configuration.py
azure/mgmt/standbypool/aio/_patch.py
azure/mgmt/standbypool/aio/operations/__init__.py
azure/mgmt/standbypool/aio/operations/_operations.py
azure/mgmt/standbypool/aio/operations/_patch.py
azure/mgmt/standbypool/models/__init__.py
azure/mgmt/standbypool/models/_enums.py
azure/mgmt/standbypool/models/_models.py
azure/mgmt/standbypool/models/_patch.py
azure/mgmt/standbypool/operations/__init__.py
azure/mgmt/standbypool/operations/_operations.py
azure/mgmt/standbypool/operations/_patch.py
azure_mgmt_standbypool-2.0.0.dist-info/LICENSE
azure_mgmt_standbypool-2.0.0.dist-info/METADATA
azure_mgmt_standbypool-2.0.0.dist-info/WHEEL
azure_mgmt_standbypool-2.0.0.dist-info/top_level.txt
azure_mgmt_standbypool-2.0.0.dist-info/RECORD
